simComponents/__init__.py
simComponents/simButton.py
simComponents/simLED.py
simComponents_dorachua-0.0.1.dist-info/LICENSE
simComponents_dorachua-0.0.1.dist-info/METADATA
simComponents_dorachua-0.0.1.dist-info/WHEEL
simComponents_dorachua-0.0.1.dist-info/top_level.txt
simComponents_dorachua-0.0.1.dist-info/RECORD
