Metadata-Version: 2.1
Name: simComponents-dorachua
Version: 0.0.1
Summary: A small package for simulating RaspberryPi and Arduino hardware components on a Windows PC
Home-page: UNKNOWN
Author: Dora Chua
Author-email: msdorachua@gmail.com
License: UNKNOWN
Platform: UNKNOWN
Classifier: Programming Language :: Python :: 3
Classifier: License :: OSI Approved :: MIT License
Classifier: Operating System :: OS Independent
Requires-Python: >=3.6
